README.md
setup.py
asyncgp/__init__.py
asyncgp/asyncgp.py
asyncgp.egg-info/PKG-INFO
asyncgp.egg-info/SOURCES.txt
asyncgp.egg-info/dependency_links.txt
asyncgp.egg-info/requires.txt
asyncgp.egg-info/top_level.txt
test/test_asyncgp.py