Metadata-Version: 2.1
Name: asyncgp
Version: 0.2.2
Summary: An asyncio Greenplum driver
Home-page: https://github.com/MyColorfulDays/asyncgp.git
Author: MyColorfulDays
Author-email: my_colorful_days@163.com
License: Apache License, Version 2.0
Platform: macOS
Platform: POSIX
Platform: Windows
Classifier: Development Status :: 1 - Planning
Classifier: Framework :: AsyncIO
Classifier: Intended Audience :: Developers
Classifier: License :: OSI Approved :: Apache Software License
Classifier: Operating System :: POSIX
Classifier: Operating System :: MacOS :: MacOS X
Classifier: Operating System :: Microsoft :: Windows
Classifier: Programming Language :: Python :: 3 :: Only
Classifier: Programming Language :: Python :: 3.5
Classifier: Programming Language :: Python :: 3.6
Classifier: Programming Language :: Python :: 3.7
Classifier: Programming Language :: Python :: Implementation :: CPython
Classifier: Topic :: Database :: Front-Ends
Requires-Python: >=3.5.0
